*
uta_align
