Metadata-Version: 2.1
Name: uta-align
Version: 0.3.0
Summary: C-based sequence alignment for Python
Author-email: biocommons contributors <biocommons-dev@googlegroups.com>
License: 
Project-URL: Homepage, https://github.com/biocommons/uta-align
Project-URL: Bug Tracker, https://github.com/biocommons/uta-align/issues
Classifier: Programming Language :: Python :: 3
Classifier: Programming Language :: Python :: 3.9
Classifier: Programming Language :: Python :: 3.10
Classifier: Programming Language :: Python :: 3.11
Classifier: License :: OSI Approved :: MIT License
Classifier: Operating System :: OS Independent
Requires-Python: >=3.9
License-File: LICENSE.txt
Requires-Dist: coloredlogs~=15.0
Requires-Dist: pysam~=0.22
Requires-Dist: pyyaml~=6.0
Provides-Extra: dev
Requires-Dist: black~=22.3; extra == "dev"
Requires-Dist: build~=0.8; extra == "dev"
Requires-Dist: flake8~=4.0; extra == "dev"
Requires-Dist: ipython~=8.4; extra == "dev"
Requires-Dist: isort~=5.10; extra == "dev"
Requires-Dist: pre-commit~=3.4; extra == "dev"
Requires-Dist: pylint~=2.14; extra == "dev"
Requires-Dist: pytest-cov~=4.1; extra == "dev"
Requires-Dist: pytest-optional-tests; extra == "dev"
Requires-Dist: pytest~=7.1; extra == "dev"
Requires-Dist: setuptools_scm~=8.0; extra == "dev"
Requires-Dist: twine~=5.0; extra == "dev"
Requires-Dist: wheel~=0.42; extra == "dev"
Provides-Extra: docs
Requires-Dist: mkdocs; extra == "docs"
